acdh_graph_pyutils/__init__.py
acdh_graph_pyutils/graph.py
acdh_graph_pyutils/namespaces.py
acdh_graph_pyutils/string_utils.py
acdh_graph_pyutils/xml.py
acdh_graph_pyutils-0.0.3.dist-info/LICENSE
acdh_graph_pyutils-0.0.3.dist-info/METADATA
acdh_graph_pyutils-0.0.3.dist-info/WHEEL
acdh_graph_pyutils-0.0.3.dist-info/top_level.txt
acdh_graph_pyutils-0.0.3.dist-info/RECORD
