Metadata-Version: 2.1
Name: acdh-graph-pyutils
Version: 0.0.3
Summary: Helper functions for the generation of RDF Graphs
Home-page: https://github.com/acdh-oeaw/acdh-graph-pyutils
Author: Daniel Elsner
Author-email: daniel.elsner@oeaw.ac.at
License: MIT license
Classifier: Intended Audience :: Developers
Classifier: License :: OSI Approved :: MIT License
Classifier: Natural Language :: English
Requires-Python: >=3.10
License-File: LICENSE
Requires-Dist: rdflib <7,>=6
Requires-Dist: acdh-tei-pyutils >=1.4
Requires-Dist: python-slugify >=8
